icolor/__init__.py
iprint/__init__.py
iprint/test.py
icecomet-4.1.0.dist-info/LICENSE
icecomet-4.1.0.dist-info/METADATA
icecomet-4.1.0.dist-info/WHEEL
icecomet-4.1.0.dist-info/top_level.txt
icecomet-4.1.0.dist-info/RECORD
